telluride_decoding/__init__.py
telluride_decoding/attention_decoder.py
telluride_decoding/brain_data.py
telluride_decoding/brain_model.py
telluride_decoding/cca.py
telluride_decoding/csv_util.py
telluride_decoding/decoding.py
telluride_decoding/infer.py
telluride_decoding/infer_decoder.py
telluride_decoding/ingest.py
telluride_decoding/ingest_brainvision.py
telluride_decoding/plot_util.py
telluride_decoding/preprocess.py
telluride_decoding/preprocess_audio.py
telluride_decoding/regression.py
telluride_decoding/regression_data.py
telluride_decoding/result_store.py
telluride_decoding/scaled_lda.py
telluride_decoding/setup.py
telluride_decoding/utils.py
telluride_decoding-2.1.6.dist-info/LICENSE
telluride_decoding-2.1.6.dist-info/METADATA
telluride_decoding-2.1.6.dist-info/WHEEL
telluride_decoding-2.1.6.dist-info/top_level.txt
telluride_decoding-2.1.6.dist-info/RECORD
