Metadata-Version: 2.1
Name: telluride-decoding
Version: 2.1.6
Summary: Telluride Decoding Toolbox
Home-page: https://github.com/google/telluride_decoding
Author: Malcolm Slaney
Author-email: telluride-decoding-maintainers@googlegroups.com
License: UNKNOWN
Platform: UNKNOWN
Classifier: Programming Language :: Python :: 3
Classifier: License :: OSI Approved :: Apache Software License
Classifier: Operating System :: OS Independent
Requires-Python: >=3.6
License-File: LICENSE
Requires-Dist: absl-py
Requires-Dist: attrs
Requires-Dist: matplotlib
Requires-Dist: mock
Requires-Dist: pandas
Requires-Dist: pyedflib
Requires-Dist: scipy
Requires-Dist: tensorflow (>=2)
